ask_orex/__init__.py
ask_orex/__main__.py
ask_orex/ask_orex.py
ask_orex/constants.py
ask_orex-1.1.2.dist-info/LICENSE
ask_orex-1.1.2.dist-info/METADATA
ask_orex-1.1.2.dist-info/WHEEL
ask_orex-1.1.2.dist-info/top_level.txt
ask_orex-1.1.2.dist-info/RECORD
