Metadata-Version: 2.1
Name: ask-orex
Version: 1.1.2
Summary: ASK-Orex: Ordinary human-friendly Regular Expressions
Author: Fernando Egoavil Cisneros
Author-email: "Arvid J. Kingl" <akingl2016@gmail.com>
Project-URL: Homepage, https://github.com/HCelion/orex
Classifier: License :: OSI Approved :: MIT License
Classifier: Programming Language :: Python
Classifier: Programming Language :: Python :: 3
License-File: LICENSE
Requires-Dist: pytest
Provides-Extra: dev
Requires-Dist: black ; extra == 'dev'
Requires-Dist: bumpver ; extra == 'dev'
Requires-Dist: isort ; extra == 'dev'
Requires-Dist: pip-tools ; extra == 'dev'
Requires-Dist: pytest ; extra == 'dev'
